jks/__init__.py
jks/corrIO.py
jks/distributions.py
jks/fit.py
jks/measurements.py
jks/resamples.py
jks_system-1.0.3.data/scripts/dump-corrs
jks_system-1.0.3.data/scripts/jks_add
jks_system-1.0.3.data/scripts/jks_add_all
jks_system-1.0.3.data/scripts/jks_add_from
jks_system-1.0.3.data/scripts/jks_add_parameter
jks_system-1.0.3.data/scripts/jks_add_sys
jks_system-1.0.3.data/scripts/jks_compress
jks_system-1.0.3.data/scripts/jks_correlator_reconstruct
jks_system-1.0.3.data/scripts/jks_create_correlator_from_corrfile
jks_system-1.0.3.data/scripts/jks_create_correlator_from_corrfile_novar
jks_system-1.0.3.data/scripts/jks_create_correlator_from_multi_textfile
jks_system-1.0.3.data/scripts/jks_create_correlator_from_textfile
jks_system-1.0.3.data/scripts/jks_create_parameter
jks_system-1.0.3.data/scripts/jks_dump_blocks
jks_system-1.0.3.data/scripts/jks_dup
jks_system-1.0.3.data/scripts/jks_extract_config
jks_system-1.0.3.data/scripts/jks_fit
jks_system-1.0.3.data/scripts/jks_gevp_2pt
jks_system-1.0.3.data/scripts/jks_gevp_2pt_basis_change
jks_system-1.0.3.data/scripts/jks_gevp_2pt_tref
jks_system-1.0.3.data/scripts/jks_info
jks_system-1.0.3.data/scripts/jks_merge
jks_system-1.0.3.data/scripts/jks_model_average
jks_system-1.0.3.data/scripts/jks_plot
jks_system-1.0.3.data/scripts/jks_plot_dist
jks_system-1.0.3.data/scripts/jks_refit0
jks_system-1.0.3.data/scripts/jks_refit1
jks_system-1.0.3.data/scripts/jks_refit1f
jks_system-1.0.3.data/scripts/jks_rescale_variance
jks_system-1.0.3.data/scripts/jks_rm
jks_system-1.0.3.data/scripts/jks_set_variance
jks_system-1.0.3.data/scripts/jks_slow_fit
jks_system-1.0.3.data/scripts/jks_sys
jks_system-1.0.3.data/scripts/jks_tagged_merge
jks_system-1.0.3.data/scripts/jks_tagged_merge_auto
jks_system-1.0.3.data/scripts/jks_take
jks_system-1.0.3.data/scripts/list-corrs
jks_system-1.0.3.dist-info/METADATA
jks_system-1.0.3.dist-info/WHEEL
jks_system-1.0.3.dist-info/top_level.txt
jks_system-1.0.3.dist-info/RECORD
