Metadata-Version: 2.4
Name: jks-system
Version: 1.0.3
Summary: JKS Measurement database system
Home-page: https://github.com/lehner/jks
Author: Christoph Lehner
Author-email: christoph@lhnr.de
Classifier: Programming Language :: Python :: 3
Classifier: License :: OSI Approved :: GNU General Public License v2 (GPLv2)
Classifier: Operating System :: OS Independent
Requires-Python: >=3.6
Requires-Dist: scipy
Requires-Dist: lz4
Requires-Dist: numpy
Dynamic: author
Dynamic: author-email
Dynamic: classifier
Dynamic: description
Dynamic: description-content-type
Dynamic: home-page
Dynamic: requires-dist
Dynamic: requires-python
Dynamic: summary
